unicorn_binance_websocket_api/__init__.py
unicorn_binance_websocket_api/api.py
unicorn_binance_websocket_api/connection.py
unicorn_binance_websocket_api/connection_settings.py
unicorn_binance_websocket_api/exceptions.py
unicorn_binance_websocket_api/manager.py
unicorn_binance_websocket_api/restclient.py
unicorn_binance_websocket_api/restserver.py
unicorn_binance_websocket_api/sockets.py
unicorn_binance_websocket_api_onion-1.46.2.dist-info/LICENSE
unicorn_binance_websocket_api_onion-1.46.2.dist-info/METADATA
unicorn_binance_websocket_api_onion-1.46.2.dist-info/WHEEL
unicorn_binance_websocket_api_onion-1.46.2.dist-info/top_level.txt
unicorn_binance_websocket_api_onion-1.46.2.dist-info/RECORD
