Metadata-Version: 2.1
Name: unicorn-binance-websocket-api-onion
Version: 1.46.2
Summary: An unofficial Python API to use the Binance Websocket API`s (com+testnet, com-margin+testnet, com-isolated_margin+testnet, com-futures+testnet, jersey, us, dex/chain+testnet) in a easy, fast, flexible, robust and fully-featured way.
Home-page: https://github.com/onionj/unicorn-binance-websocket-api
Author: LUCIT Systems and Development
Author-email: info@lucit.tech
License: MIT License
Project-URL: Howto, https://www.lucit.tech/unicorn-binance-websocket-api.html#howto
Project-URL: Documentation, https://unicorn-binance-websocket-api.docs.lucit.tech
Project-URL: Wiki, https://github.com/LUCIT-Systems-and-Development/unicorn-binance-websocket-api/wiki
Project-URL: Author, https://www.lucit.tech
Project-URL: Changes, https://unicorn-binance-websocket-api.docs.lucit.tech//CHANGELOG.html
Project-URL: Issue Tracker, https://github.com/LUCIT-Systems-and-Development/unicorn-binance-websocket-api/issues
Project-URL: Chat, https://gitter.im/unicorn-binance-suite/unicorn-binance-websocket-api
Project-URL: Telegram, https://t.me/unicorndevs
Project-URL: Get Support, https://www.lucit.tech/get-support.html
Keywords: binance,asyncio,async,asynchronous,concurrent,websocket-api,webstream-api,binance-websocket,binance-webstream,webstream,websocket,api,binance-jersey,binance-dex,binance-futures,binance-margin,binance-us
Classifier: Development Status :: 5 - Production/Stable
Classifier: Programming Language :: Python :: 3.7
Classifier: Programming Language :: Python :: 3.8
Classifier: Programming Language :: Python :: 3.9
Classifier: Programming Language :: Python :: 3.10
Classifier: Programming Language :: Python :: 3.11
Classifier: License :: OSI Approved :: MIT License
Classifier: Intended Audience :: Developers
Classifier: Intended Audience :: Financial and Insurance Industry
Classifier: Intended Audience :: Information Technology
Classifier: Intended Audience :: Science/Research
Classifier: Operating System :: OS Independent
Classifier: Topic :: Office/Business :: Financial :: Investment
Classifier: Topic :: Software Development :: Libraries :: Python Modules
Classifier: Framework :: AsyncIO
Requires-Python: >=3.7.0
License-File: LICENSE
Requires-Dist: colorama
Requires-Dist: requests
Requires-Dist: websocket-client
Requires-Dist: websockets>=10.4
Requires-Dist: flask_restful
Requires-Dist: cheroot
Requires-Dist: flask
Requires-Dist: ujson
Requires-Dist: psutil
Requires-Dist: PySocks
Requires-Dist: unicorn-fy
Requires-Dist: unicorn-binance-rest-api>=1.9.0
Requires-Dist: typing_extensions
